{"type":"FeatureCollection","totalFeatures":4,"features":[{"type":"Feature","id":"OSS_TotaleEventiStazioni.fid--33711477_18b1998dabe_-2cc2","geometry":{"type":"Point","coordinates":[14.22917,40.85694]},"geometry_name":"PosizioneEdificio","properties":{"IdEvento":4171,"IdIngv":36365741,"DataOra_eve":"2023-10-02T19:08:26Z","Magnitudo":4,"Profondita":3,"SiglaStazione":"BC007","NomeEdificio":"Scuola Media \"S.Minucci\"","ComuneStaz":"NAPOLI","Lat":40.85694,"Long":14.22917,"Distanza":7,"DriftMax":0.07,"DataOra_staz":"2023-10-02T19:08:19Z","ClasseTipologica":"Edificio in cemento armato","Classificazione":"SCUOLA","cod_leg":1}},{"type":"Feature","id":"OSS_TotaleEventiStazioni.fid--33711477_18b1998dabe_-2cc1","geometry":{"type":"Point","coordinates":[14.07305556,40.84888889]},"geometry_name":"PosizioneEdificio","properties":{"IdEvento":4171,"IdIngv":36365741,"DataOra_eve":"2023-10-02T19:08:26Z","Magnitudo":4,"Profondita":3,"SiglaStazione":"EB631","NomeEdificio":"Ospedale Santa Maria delle Grazie","ComuneStaz":"POZZUOLI","Lat":40.84888889,"Long":14.07305556,"Distanza":7,"DriftMax":0.03,"DataOra_staz":"2023-10-02T19:08:21Z","ClasseTipologica":"Edificio in cemento armato","Classificazione":"OSPEDALE","cod_leg":1}},{"type":"Feature","id":"OSS_TotaleEventiStazioni.fid--33711477_18b1998dabe_-2cc0","geometry":{"type":"Point","coordinates":[14.165,40.81361111]},"geometry_name":"PosizioneEdificio","properties":{"IdEvento":4171,"IdIngv":36365741,"DataOra_eve":"2023-10-02T19:08:26Z","Magnitudo":4,"Profondita":3,"SiglaStazione":"EB624","NomeEdificio":"ITN Duca degli Abruzzi","ComuneStaz":"NAPOLI","Lat":40.81361111,"Long":14.165,"Distanza":2,"DriftMax":0.1,"DataOra_staz":"2023-10-02T19:08:18Z","ClasseTipologica":"Edificio in cemento armato","Classificazione":"SCUOLA","cod_leg":1}},{"type":"Feature","id":"OSS_TotaleEventiStazioni.fid--33711477_18b1998dabe_-2cbf","geometry":{"type":"Point","coordinates":[14.0725,40.81611111]},"geometry_name":"PosizioneEdificio","properties":{"IdEvento":4171,"IdIngv":36365741,"DataOra_eve":"2023-10-02T19:08:26Z","Magnitudo":4,"Profondita":3,"SiglaStazione":"EB637","NomeEdificio":"Ufficio Locale Marittimo","ComuneStaz":"BACOLI","Lat":40.81611111,"Long":14.0725,"Distanza":7,"DriftMax":0.01,"DataOra_staz":"2023-10-02T19:08:20Z","ClasseTipologica":"Edificio in muratura","Classificazione":"ALTRO EDIFICIO","cod_leg":2}}],"crs":{"type":"name","properties":{"name":"urn:ogc:def:crs:EPSG::4326"}}}